sample_package/__init__.py
sample_package/main.py
sample_package_nivin-0.1.0.dist-info/LICENSE
sample_package_nivin-0.1.0.dist-info/METADATA
sample_package_nivin-0.1.0.dist-info/WHEEL
sample_package_nivin-0.1.0.dist-info/RECORD
